images_rs-0.1.1.dist-info/METADATA
images_rs-0.1.1.dist-info/WHEEL
images_rs/__init__.py
images_rs/images_rs.abi3.so
images_rs-0.1.1.dist-info/RECORD
